Metadata-Version: 1.0
Name: distributions-probabilities
Version: 1.2
Summary: Gaussian and binomial distribution
Home-page: UNKNOWN
Author: Alexander Karari
Author-email: mc8testmail@gmail.com
License: UNKNOWN
Platform: UNKNOWN
